pretix_printtool/__init__.py
pretix_printtool/config.py
pretix_printtool/main.py
pretix_printtool/printing.py
pretix_printtool/testing.py
pretix_printtool-0.1.1.dist-info/DESCRIPTION.rst
pretix_printtool-0.1.1.dist-info/METADATA
pretix_printtool-0.1.1.dist-info/RECORD
pretix_printtool-0.1.1.dist-info/WHEEL
pretix_printtool-0.1.1.dist-info/entry_points.txt
pretix_printtool-0.1.1.dist-info/metadata.json
pretix_printtool-0.1.1.dist-info/top_level.txt
