Metadata-Version: 2.0
Name: pretix-printtool
Version: 0.1.1
Summary: Command-line client for pretix that allows to print out tickets for shippinh
Home-page: https://github.com/pretix/pretix-printtool
Author: Raphael Michel
Author-email: mail@raphaelmichel.de
License: UNKNOWN
Platform: UNKNOWN
Requires-Dist: click (==6.*)
Requires-Dist: pycups
Requires-Dist: requests
